mldev/__init__.py
mldev/experiment.py
mldev/experiment_objects.py
mldev/experiment_tag.py
mldev/expression.py
mldev/init_git.sh
mldev/init_lfs.sh
mldev/init_template.sh
mldev/init_venv.sh
mldev/install_ngrok.sh
mldev/main.py
mldev/ngrok_urls.sh
mldev/python_context.py
mldev/utils.py
mldev/version.py
mldev/yaml_loader.py
mldev_bot/__init__.py
mldev_bot/app.py
mldev_bot/bot_service.py
mldev_bot/config.json
mldev_bot/proxy.py
mldev_bot/requirements.txt
mldev_collab/__init__.py
mldev_collab/collab.py
mldev_collab/init_collab.sh
mldev_collab/operations.py
mldev_collab/requirements.txt
mldev_config_parser/__init__.py
mldev_config_parser/config_parser.py
mldev_config_parser/requirements.txt
mldev_controller/__init__.py
mldev_controller/controller_service.py
mldev_controller/flaskModelController.py
mldev_controller/requirements.txt
mldev_dvc/__init__.py
mldev_dvc/dvc_stage.py
mldev_dvc/init_dvc.sh
mldev_jupyter/__init__.py
mldev_jupyter/ipython.py
mldev_jupyter/requirements.txt
mldev_tensorboard/__init__.py
mldev_tensorboard/requirements.txt
mldev_tensorboard/tensorboard_service.py
mldev-0.5.0.dev1.dist-info/LICENSE
mldev-0.5.0.dev1.dist-info/METADATA
mldev-0.5.0.dev1.dist-info/NOTICE.md
mldev-0.5.0.dev1.dist-info/WHEEL
mldev-0.5.0.dev1.dist-info/entry_points.txt
mldev-0.5.0.dev1.dist-info/top_level.txt
mldev-0.5.0.dev1.dist-info/RECORD
